liveflask/__init__.py
liveflask/utils.py
liveflask/attributes/__init__.py
liveflask/static/lodash.min.js
liveflask/static/liveflask/action.js
liveflask/static/liveflask/constants.js
liveflask/static/liveflask/events.js
liveflask/static/liveflask/init.js
liveflask/static/liveflask/liveflask.js
liveflask/static/liveflask/model.js
liveflask/static/liveflask/polling.js
liveflask/static/liveflask/utils.js
liveflask/templates/liveflask-head.html
liveflask/templates/liveflask-scripts.html
liveflask/traits/Bootable.py
liveflask/traits/__init__.py
liveflask/traits/has_actions.py
liveflask/traits/has_props.py
liveflask/traits/has_renders.py
liveflask/traits/has_snapshots.py
liveflask/traits/has_synthesizer.py
liveflask-1.0.23.dist-info/METADATA
liveflask-1.0.23.dist-info/WHEEL
liveflask-1.0.23.dist-info/top_level.txt
liveflask-1.0.23.dist-info/RECORD
